image_sorting_tool/__init__.py
image_sorting_tool/__main__.py
image_sorting_tool/gui.py
image_sorting_tool/image_sort.py
image_sorting_tool-1.2.0.dist-info/LICENSE
image_sorting_tool-1.2.0.dist-info/METADATA
image_sorting_tool-1.2.0.dist-info/WHEEL
image_sorting_tool-1.2.0.dist-info/entry_points.txt
image_sorting_tool-1.2.0.dist-info/top_level.txt
image_sorting_tool-1.2.0.dist-info/RECORD
