Metadata-Version: 2.1
Name: image-sorting-tool
Version: 1.2.0
Summary: Graphical tool to sort images into a folder structure based on the date the images were taken
Home-page: https://github.com/ThorpeJosh/image-sorting-tool
Author: Joshua Thorpe
Author-email: josh@thorpe.engineering
License: MIT
Keywords: image,sort,gui,executable
Classifier: License :: OSI Approved :: MIT License
Classifier: Programming Language :: Python
Classifier: Programming Language :: Python :: 3
Classifier: Programming Language :: Python :: 3.9
Classifier: Programming Language :: Python :: 3.10
Classifier: Programming Language :: Python :: 3.11
Classifier: Programming Language :: Python :: 3.12
Classifier: Programming Language :: Python :: 3.13
Classifier: Operating System :: Microsoft :: Windows
Classifier: Operating System :: POSIX :: Linux
Classifier: Operating System :: MacOS
Requires-Python: >=3.9, <3.14
License-File: LICENSE
Requires-Dist: Pillow ~=11.0.0
Requires-Dist: python-dateutil ~=2.8
Provides-Extra: dev
Requires-Dist: pytest ==8.3.* ; extra == 'dev'
Requires-Dist: pylint ==3.3.* ; extra == 'dev'
Requires-Dist: black ==24.10.* ; extra == 'dev'
Requires-Dist: setuptools ==75.2.* ; extra == 'dev'
